moic/__init__.py
moic/base.py
moic/cli/__init__.py
moic/cli/base.py
moic/cli/commands/__init__.py
moic/cli/commands/context/__init__.py
moic/cli/commands/context/base.py
moic/cli/commands/issue/__init__.py
moic/cli/commands/issue/base.py
moic/cli/commands/rabbit/__init__.py
moic/cli/commands/rabbit/base.py
moic/cli/commands/resources/__init__.py
moic/cli/commands/resources/base.py
moic/cli/commands/template/__init__.py
moic/cli/commands/template/base.py
moic/cli/commands/version.py
moic/cli/completion/__init__.py
moic/cli/completion/base.py
moic/cli/utils/__init__.py
moic/cli/utils/base.py
moic/cli/validators/__init__.py
moic/cli/validators/base.py
moic/plugins/__init__.py
moic/plugins/jira/__init__.py
moic/plugins/jira/api.py
moic/plugins/jira/base.py
moic/plugins/jira/commands/__init__.py
moic/plugins/jira/commands/issue/__init__.py
moic/plugins/jira/commands/issue/base.py
moic/plugins/jira/commands/resources/__init__.py
moic/plugins/jira/commands/resources/base.py
moic/plugins/jira/commands/sprint/__init__.py
moic/plugins/jira/commands/sprint/base.py
moic/plugins/jira/completion/__init__.py
moic/plugins/jira/completion/base.py
moic/plugins/jira/core.py
moic/plugins/jira/utils/__init__.py
moic/plugins/jira/utils/base.py
moic/plugins/jira/utils/parser.py
moic/plugins/jira/validators/__init__.py
moic/plugins/jira/validators/base.py
moic-1.3.1.dist-info/entry_points.txt
moic-1.3.1.dist-info/WHEEL
moic-1.3.1.dist-info/METADATA
moic-1.3.1.dist-info/RECORD
