Metadata-Version: 2.1
Name: moic
Version: 1.3.1
Summary: My Own Issue CLI (Jira, Gitlab etc...)
Home-page: https://moic.readthedocs.io/
Author: Brice Santus
Author-email: brice.santus@gmail.com
Requires-Python: >=3.7,<4.0
Classifier: Environment :: Console
Classifier: Intended Audience :: Developers
Classifier: Intended Audience :: End Users/Desktop
Classifier: Operating System :: POSIX :: Linux
Classifier: Programming Language :: Python :: 3
Classifier: Programming Language :: Python :: 3.7
Classifier: Programming Language :: Python :: 3.8
Provides-Extra: docs
Requires-Dist: antidote (>=0.7.0,<0.8.0)
Requires-Dist: click (>=7.1.1,<8.0.0)
Requires-Dist: commonmark (>=0.9.1,<0.10.0)
Requires-Dist: dynaconf (>=2.2.3,<3.0.0)
Requires-Dist: jira
Requires-Dist: keyring (>=21.1.1,<22.0.0)
Requires-Dist: pyyaml (>=5.3,<6.0)
Requires-Dist: rich (>=0.8.8,<0.9.0)
Requires-Dist: tomd (>=0.1.3,<0.2.0)
Project-URL: Documentation, https://moic.readthedocs.io/
Project-URL: Repository, https://gitlab.com/brice.santus/moic
